{
  "name": "Barrington BR FR401 Double French Horn",
  "price": "$280.00 – $350.75Price range: $280.00 through $350.75",
  "sku": "N/A",
  "category": "Band & Orchestra",
  "description": "",
  "fullDescription": "Description\n\nFusce nunc dolor, pretium luctus elit at, interdum sollicitudin lectus. Quisque finibus consequat molestie. Aenean cursus lorem eu fringilla euismod. Pellentesque ullamcorper tempus nisl at sollicitudin. Ut ut maximus lectus, ut condimentum augue. Curabitur non tortor neque. Donec euismod diam sit amet pretium molestie. Sed quis pellentesque velit, vitae rhoncus dolor. Aliquam erat volutpat. Aenean malesuada, risus sed lobortis iaculis, massa erat tristique purus, eu suscipit magna ipsum eu elit. Ut eu orci eget est vestibulum pretium quis ultrices eros.\nMauris non rhoncus mauris, ut porta nunc. Nullam tincidunt tempus ligula, a dapibus massa ullamcorper et. Aliquam facilisis, massa in malesuada vehicula, odio mauris gravida sem, molestie imperdiet metus urna sit amet ex. Praesent egestas, nisi vel finibus finibus, dui nulla aliquam metus, sit amet lacinia diam justo sed mauris. Sed efficitur, eros vitae ultricies bibendum, eros nibh pretium massa, ut consequat nisl felis eu libero. Aenean sit amet convallis nisl. Vestibulum sollicitudin nec sem sit amet aliquam. Integer rutrum vel neque nec porttitor. Integer malesuada at massa at vulputate. Duis in nunc molestie, vulputate erat a, interdum tellus. Vestibulum eget nisl ullamcorper, mattis nisi sed, mollis nibh. Maecenas semper, erat a porttitor rutrum, metus nulla accumsan ligula, nec faucibus lorem risus ac enim.",
  "stock": "",
  "rating": "",
  "image": "https://musicplace.themerex.net/wp-content/uploads/2016/08/horn-600x777.jpg",
  "url": "https://musicplace.themerex.net/product/barrington-br-fr401-double-french-horn/"
}